{
  "name": "Zitu Kundu",
  "title": "Graduate Researcher",
  "department": "Department of Geology & Mining",
  "university": "University of Barishal, Bangladesh",
  "email": "zitukundu01@gmail.com",
  "phone": "+880 1789 971 249",
  "address": "Kornokathi, Barishal — 8254, Bangladesh",
  "bio": "Zitu Kundu is a graduate researcher at the Department of Geology & Mining, University of Barishal, Bangladesh. His MS thesis — currently defended — is titled \"A Comprehensive Geochemical Investigation of the Kuakata Beach Sand: Implications for Provenance, Weathering, Heavy Metal Contamination, and Natural Radioactivity.\" His research works with major oxides, trace elements, and rare earth elements (REEs) to constrain sediment provenance, weathering history, and geochemical conditions of the Bengal coastal system. He also conducts radiological risk assessment, health risk assessment, and spatial distribution analysis of heavy metals and NORMs.",
  "ielts": "6.0 (Retake in Progress)",
  "supervisor": "Dr. Dhiman Kumer Roy",
  "graduation": "April / May 2026"
}
